hyssop_extension/component/__init__.py
hyssop_extension/component/orm/__init__.py
hyssop_extension/component/orm/constants.py
hyssop_extension/component/orm/entity.py
hyssop_extension/component/orm/executor_pool.py
hyssop_extension/component/orm/local.csv
hyssop_extension/component/orm/orm.py
hyssop_extension/component/orm/utils.py
hyssop_extension/unit_test/__init__.py
hyssop_extension/unit_test/orm.py
hyssop_extension-1.0.1.dist-info/LICENSE
hyssop_extension-1.0.1.dist-info/METADATA
hyssop_extension-1.0.1.dist-info/WHEEL
hyssop_extension-1.0.1.dist-info/top_level.txt
hyssop_extension-1.0.1.dist-info/RECORD
