Metadata-Version: 2.1
Name: hyssop-extension
Version: 1.0.1
Summary: Extended hyssop components and utilities
Home-page: https://github.com/hsky77/hyssop
Author: hsky77
Author-email: howardlkung@gmail.com
License: MIT License
Platform: UNKNOWN
Classifier: Programming Language :: Python :: 3
Classifier: Programming Language :: Python :: 3.6
Classifier: Programming Language :: Python :: 3.7
Classifier: License :: OSI Approved :: MIT License
Classifier: Operating System :: OS Independent
Requires-Python: >=3.6
Requires-Dist: hyssop (>=1.0.1)
Requires-Dist: sqlalchemy (>=1.3.5)
